{
  "project_info": {
    "project_number": "589531730232",
    "firebase_url": "https://fakebook-40da5.firebaseio.com",
    "project_id": "fakebook-40da5",
    "storage_bucket": "fakebook-40da5.appspot.com"
  },
  "client": [
    {
      "client_info": {
        "mobilesdk_app_id": "1:589531730232:android:3d5812ac82c4a1f7a371cd",
        "android_client_info": {
          "package_name": "com.fb"
        }
      },
      "oauth_client": [
        {
          "client_id": "589531730232-l84roasoscdg5brrrti164c6bpie6kc8.apps.googleusercontent.com",
          "client_type": 3
        }
      ],
      "api_key": [
        {
          "current_key": "AIzaSyCX6oMygaY00Crq9CvgtE9lBqO9KgxG2-o"
        }
      ],
      "services": {
        "appinvite_service": {
          "other_platform_oauth_client": [
            {
              "client_id": "589531730232-l84roasoscdg5brrrti164c6bpie6kc8.apps.googleusercontent.com",
              "client_type": 3
            }
          ]
        }
      }
    }
  ],
  "configuration_version": "1"
}